blackline/__main__.py
blackline/constants.py
blackline/exceptions.py
blackline/version.py
blackline/adapters/base.py
blackline/adapters/sql/__init__.py
blackline/adapters/sql/sql.py
blackline/adapters/sqlite/__init__.py
blackline/adapters/sqlite/sqlite.py
blackline/cli/__init__.py
blackline/cli/cli.py
blackline/execution/__init__.py
blackline/execution/audit.py
blackline/execution/debug.py
blackline/execution/deidentify.py
blackline/execution/demo.py
blackline/execution/report.py
blackline/execution/validate.py
blackline/factories/__init__.py
blackline/factories/adapter.py
blackline/factories/query.py
blackline/models/catalogue.py
blackline/models/collection.py
blackline/models/datastore_base.py
blackline/models/datastores.py
blackline/models/project_config.py
blackline/models/template.py
blackline/models/validation.py
blackline/models/sqlite/__init__.py
blackline/models/sqlite/sqlite.py
blackline/project/__init__.py
blackline/project/init.py
blackline/project/templates/__init__.py
blackline/project/templates/blackline_project.yml
blackline/query/__init__.py
blackline/query/template.py
blackline/query/templates.py
blackline/utils/__init__.py
blackline/utils/default_fixtures.py
blackline/utils/doc_examples.py
blackline/utils/testing/__init__.py
blackline/utils/testing/conftest_shared.py
blackline/utils/testing/raw_yaml.py
tests/conftest.py
tests/conftest_sqlite.py
tests/adapters/test_sqlite_adapter.py
tests/cli/test_cli.py
tests/execution/test_debug.py
tests/execution/test_deifentify.py
tests/execution/test_demo.py
tests/execution/test_report.py
tests/execution/test_validate.py
tests/factories/test_adapter_factory.py
tests/factories/test_query_factory.py
tests/models/test_catalogue.py
tests/models/test_datastores.py
tests/models/test_project_config.py
tests/models/test_sqlite.py
tests/models/test_validation.py
tests/project/test_init_project.py
tests/query/test_template_query.py
tests/utils/test_doc_examples.py
blackline_core-0.1.2.dist-info/METADATA
blackline_core-0.1.2.dist-info/WHEEL
blackline_core-0.1.2.dist-info/entry_points.txt
blackline_core-0.1.2.dist-info/top_level.txt
blackline_core-0.1.2.dist-info/RECORD
